README.rst
setup.py
txjuju/__init__.py
txjuju/_juju1.py
txjuju/_juju2.py
txjuju/_utils.py
txjuju/api.py
txjuju/api_data.py
txjuju/cli.py
txjuju/config.py
txjuju/errors.py
txjuju/protocol.py
txjuju/status.py
txjuju.egg-info/PKG-INFO
txjuju.egg-info/SOURCES.txt
txjuju.egg-info/dependency_links.txt
txjuju.egg-info/requires.txt
txjuju.egg-info/top_level.txt
txjuju/_twisted/__init__.py
txjuju/_twisted/websockets.py
txjuju/_twisted/websocketsclient.py
txjuju/testing/__init__.py
txjuju/testing/api.py
txjuju/testing/cli.py
txjuju/testing/fakejuju.py
txjuju/testing/status.py