Metadata-Version: 1.1
Name: txjuju
Version: 0.9.0a2
Summary: A twisted-based Juju client.
Home-page: https://github.com/juju/txjuju
Author: Canonical Landscape team
Author-email: juju@lists.ubuntu.com
License: LGPLv3
Platform: UNKNOWN
Requires: Twisted
Requires: PyYAML
Requires: fixtures
Requires: testtools
